elifearticle/__init__.py
elifearticle/article.py
elifearticle/parse.py
elifearticle/utils.py
elifearticle-0.26.0.dist-info/LICENSE
elifearticle-0.26.0.dist-info/METADATA
elifearticle-0.26.0.dist-info/WHEEL
elifearticle-0.26.0.dist-info/top_level.txt
elifearticle-0.26.0.dist-info/RECORD
