Metadata-Version: 2.1
Name: elifearticle
Version: 0.26.0
Summary: eLife article objects.
Home-page: https://github.com/elifesciences/elife-article
Maintainer: eLife Sciences Publications Ltd.
Maintainer-email: tech-team@elifesciences.org
License: MIT
Classifier: Development Status :: 3 - Alpha
Classifier: Intended Audience :: Developers
Classifier: License :: OSI Approved :: MIT License
Classifier: Programming Language :: Python :: 3
License-File: LICENSE
Requires-Dist: elifetools >=0.45.0
Requires-Dist: GitPython
